ftxapi/__init__.py
ftxapi/client.py
ftxapi/version.py
ftxapi/rest/__init__.py
ftxapi/rest/ftx_rest.py
ftxapi/utils/__init__.py
ftxapi/utils/custom_logger.py
ftxapi/utils/decimal.py
ftx_api_py-0.0.1.dist-info/METADATA
ftx_api_py-0.0.1.dist-info/WHEEL
ftx_api_py-0.0.1.dist-info/top_level.txt
ftx_api_py-0.0.1.dist-info/RECORD
